{
	"cmake" : 
	{
		"generator" : 
		{
			"multiConfig" : false,
			"name" : "Ninja"
		},
		"paths" : 
		{
			"cmake" : "D:/smoke/visual cancer/Common7/IDE/CommonExtensions/Microsoft/CMake/CMake/bin/cmake.exe",
			"cpack" : "D:/smoke/visual cancer/Common7/IDE/CommonExtensions/Microsoft/CMake/CMake/bin/cpack.exe",
			"ctest" : "D:/smoke/visual cancer/Common7/IDE/CommonExtensions/Microsoft/CMake/CMake/bin/ctest.exe",
			"root" : "D:/smoke/visual cancer/Common7/IDE/CommonExtensions/Microsoft/CMake/CMake/share/cmake-3.29"
		},
		"version" : 
		{
			"isDirty" : false,
			"major" : 3,
			"minor" : 29,
			"patch" : 5,
			"string" : "3.29.5-msvc4",
			"suffix" : "msvc4"
		}
	},
	"objects" : 
	[
		{
			"jsonFile" : "codemodel-v2-ba0a2a7753f737953cc7.json",
			"kind" : "codemodel",
			"version" : 
			{
				"major" : 2,
				"minor" : 7
			}
		},
		{
			"jsonFile" : "cache-v2-111ee45da1d1824097ba.json",
			"kind" : "cache",
			"version" : 
			{
				"major" : 2,
				"minor" : 0
			}
		},
		{
			"jsonFile" : "cmakeFiles-v1-35f17c188da52ef15e68.json",
			"kind" : "cmakeFiles",
			"version" : 
			{
				"major" : 1,
				"minor" : 0
			}
		},
		{
			"jsonFile" : "toolchains-v1-bd605fa3eaa554daa737.json",
			"kind" : "toolchains",
			"version" : 
			{
				"major" : 1,
				"minor" : 0
			}
		}
	],
	"reply" : 
	{
		"client-MicrosoftVS" : 
		{
			"query.json" : 
			{
				"requests" : 
				[
					{
						"kind" : "cache",
						"version" : 2
					},
					{
						"kind" : "cmakeFiles",
						"version" : 1
					},
					{
						"kind" : "codemodel",
						"version" : 2
					},
					{
						"kind" : "toolchains",
						"version" : 1
					}
				],
				"responses" : 
				[
					{
						"jsonFile" : "cache-v2-111ee45da1d1824097ba.json",
						"kind" : "cache",
						"version" : 
						{
							"major" : 2,
							"minor" : 0
						}
					},
					{
						"jsonFile" : "cmakeFiles-v1-35f17c188da52ef15e68.json",
						"kind" : "cmakeFiles",
						"version" : 
						{
							"major" : 1,
							"minor" : 0
						}
					},
					{
						"jsonFile" : "codemodel-v2-ba0a2a7753f737953cc7.json",
						"kind" : "codemodel",
						"version" : 
						{
							"major" : 2,
							"minor" : 7
						}
					},
					{
						"jsonFile" : "toolchains-v1-bd605fa3eaa554daa737.json",
						"kind" : "toolchains",
						"version" : 
						{
							"major" : 1,
							"minor" : 0
						}
					}
				]
			}
		}
	}
}
